pyAGI/__init__.py
pyAGI/prompts.py
pyAGI/pyAGIChainGenerator.py
pyAGI/pyagi.py
pyAGI/utils.py
pyAGI-1.0.4.dist-info/LICENSE
pyAGI-1.0.4.dist-info/METADATA
pyAGI-1.0.4.dist-info/WHEEL
pyAGI-1.0.4.dist-info/top_level.txt
pyAGI-1.0.4.dist-info/RECORD
